{"frameRate":24,"name":"lucky7_icon_1","version":"5.5","compatibleVersion":"5.5","armature":[{"type":"MovieClip","frameRate":24,"name":"lucky7_icon_1","bone":[{"name":"root"},{"name":"icon bai","parent":"root"},{"name":"Comp 551_00","parent":"root"},{"name":"Comp 5_00","parent":"root"}],"slot":[{"displayIndex":-1,"name":"icon bai","parent":"icon bai"},{"blendMode":"add","displayIndex":-1,"name":"Comp 551_00","parent":"Comp 551_00"},{"blendMode":"add","displayIndex":-1,"name":"Comp 5_00","parent":"Comp 5_00"}],"skin":[{"slot":[{"name":"Comp 551_00","display":[{"name":"Comp 551_00"}]},{"name":"Comp 5_00","display":[{"name":"Comp 5_00"},{"name":"Comp 5_01"},{"name":"Comp 5_02"},{"name":"Comp 5_03"},{"name":"Comp 5_04"},{"name":"Comp 5_05"},{"name":"Comp 5_06"},{"name":"Comp 5_07"},{"name":"Comp 5_08"},{"name":"Comp 5_09"},{"name":"Comp 5_10"},{"name":"Comp 5_11"},{"name":"Comp 5_12"},{"name":"Comp 5_13"},{"name":"Comp 5_14"},{"name":"Comp 5_15"},{"name":"Comp 5_16"},{"name":"Comp 5_17"},{"name":"Comp 5_18"},{"name":"Comp 5_19"},{"name":"Comp 5_20"},{"name":"Comp 5_21"},{"name":"Comp 5_22"},{"name":"Comp 5_23"}]},{"name":"icon bai","display":[{"name":"icon bai"}]}]}],"animation":[{"duration":36,"playTimes":0,"name":"lucky7_icon_1","bone":[{"name":"icon bai","scaleFrame":[{"duration":18,"curve":[0.5,0,0.5,1]},{"duration":18,"curve":[0.5,0,0.5,1],"x":1.1,"y":1.1},{"duration":0}]},{"name":"Comp 551_00","scaleFrame":[{},{"duration":17,"curve":[0.5,0,0.5,1]},{"duration":17,"curve":[0.5,0,0.5,1],"x":1.1,"y":1.1},{}]},{"name":"Comp 5_00","scaleFrame":[{"duration":5},{"duration":31,"x":2,"y":2}]}],"slot":[{"name":"icon bai","displayFrame":[{"duration":36}]},{"name":"Comp 551_00","displayFrame":[{"value":-1},{"duration":35}],"colorFrame":[{},{"duration":17,"curve":[0.5,0,0.5,1],"value":{"aM":0}},{"duration":17,"curve":[0.5,0,0.5,1]},{"value":{"aM":0}}]},{"name":"Comp 5_00","displayFrame":[{"duration":5,"value":-1},{},{"value":1},{"value":2},{"value":3},{"value":4},{"value":5},{"value":6},{"value":7},{"value":8},{"value":9},{"value":10},{"duration":2,"value":11},{"value":12},{"value":13},{"value":14},{"value":15},{"value":16},{"value":17},{"value":18},{"value":19},{"value":20},{"value":21},{"value":22},{"duration":7,"value":23}],"colorFrame":[{"duration":29},{},{"duration":6,"value":{"aM":0}}]}]}],"defaultActions":[{"gotoAndPlay":"lucky7_icon_1"}]}]}