{"width":256,"imagePath":"rdsg_mega_tex.png","height":512,"name":"rdsg_mega","SubTexture":[{"frameHeight":720,"y":281,"frameX":-540,"width":80,"frameY":-341,"height":38,"name":"Comp 8_04","frameWidth":1280,"x":1},{"frameHeight":720,"y":41,"frameX":-558,"width":130,"frameY":-341,"height":38,"name":"Comp 8_10","frameWidth":1280,"x":1},{"frameHeight":720,"y":321,"frameX":-540,"width":57,"frameY":-341,"height":38,"name":"Comp 8_02","frameWidth":1280,"x":60},{"frameHeight":720,"y":1,"frameX":-547,"width":130,"frameY":-341,"height":38,"name":"Comp 8_09","frameWidth":1280,"x":1},{"frameHeight":720,"y":321,"frameX":-705,"width":35,"frameY":-341,"height":38,"name":"Comp 8_23","frameWidth":1280,"x":214},{"frameHeight":720,"y":201,"frameX":-638,"width":102,"frameY":-341,"height":38,"name":"Comp 8_17","frameWidth":1280,"x":131},{"frameHeight":720,"y":201,"frameX":-605,"width":128,"frameY":-341,"height":38,"name":"Comp 8_14","frameWidth":1280,"x":1},{"frameHeight":720,"y":41,"frameX":-541,"width":107,"frameY":-341,"height":38,"name":"Comp 8_07","frameWidth":1280,"x":133},{"frameHeight":720,"y":321,"frameX":-540,"width":46,"frameY":-341,"height":38,"name":"Comp 8_01","frameWidth":1280,"x":119},{"frameHeight":720,"y":1,"frameX":-627,"width":113,"frameY":-341,"height":38,"name":"Comp 8_16","frameWidth":1280,"x":133},{"frameHeight":720,"y":161,"frameX":-592,"width":128,"frameY":-341,"height":38,"name":"Comp 8_13","frameWidth":1280,"x":1},{"frameHeight":720,"y":281,"frameX":-665,"width":75,"frameY":-341,"height":38,"name":"Comp 8_19","frameWidth":1280,"x":83},{"frameHeight":720,"y":321,"frameX":-695,"width":45,"frameY":-341,"height":38,"name":"Comp 8_22","frameWidth":1280,"x":167},{"frameHeight":720,"y":241,"frameX":-671,"width":69,"frameY":-341,"height":38,"name":"Comp 8_20","frameWidth":1280,"x":184},{"frameHeight":720,"y":161,"frameX":-614,"width":124,"frameY":-341,"height":38,"name":"Comp 8_15","frameWidth":1280,"x":131},{"frameHeight":720,"y":281,"frameX":-540,"width":68,"frameY":-341,"height":38,"name":"Comp 8_03","frameWidth":1280,"x":160},{"frameHeight":720,"y":361,"frameX":-540,"width":34,"frameY":-341,"height":38,"name":"Comp 8_00","frameWidth":1280,"x":1},{"frameHeight":720,"y":241,"frameX":-648,"width":92,"frameY":-341,"height":38,"name":"Comp 8_18","frameWidth":1280,"x":1},{"frameHeight":720,"y":241,"frameX":-540,"width":87,"frameY":-341,"height":38,"name":"Comp 8_05","frameWidth":1280,"x":95},{"frameHeight":720,"y":121,"frameX":-581,"width":129,"frameY":-341,"height":38,"name":"Comp 8_12","frameWidth":1280,"x":1},{"frameHeight":720,"y":321,"frameX":-683,"width":57,"frameY":-341,"height":38,"name":"Comp 8_21","frameWidth":1280,"x":1},{"frameHeight":720,"y":81,"frameX":-540,"width":103,"frameY":-341,"height":38,"name":"Comp 8_06","frameWidth":1280,"x":133},{"frameHeight":720,"y":81,"frameX":-569,"width":130,"frameY":-341,"height":38,"name":"Comp 8_11","frameWidth":1280,"x":1},{"frameHeight":720,"y":121,"frameX":-542,"width":123,"frameY":-341,"height":38,"name":"Comp 8_08","frameWidth":1280,"x":132}]}