{"frameRate":24,"name":"sdmn_megawin_ani","version":"5.5","compatibleVersion":"5.5","armature":[{"type":"MovieClip","frameRate":24,"name":"sdmn_megawin_ani","bone":[{"name":"root"},{"name":"Comp 101_00","parent":"root"}],"slot":[{"blendMode":"add","displayIndex":-1,"name":"Comp 101_00","parent":"Comp 101_00"}],"skin":[{"slot":[{"name":"Comp 101_00","display":[{"name":"Comp 101_00"},{"name":"Comp 101_01"},{"name":"Comp 101_02"},{"name":"Comp 101_03"},{"name":"Comp 101_04"},{"name":"Comp 101_05"},{"name":"Comp 101_06"},{"name":"Comp 101_07"},{"name":"Comp 101_08"},{"name":"Comp 101_09"},{"name":"Comp 101_10"},{"name":"Comp 101_11"},{"name":"Comp 101_12"},{"name":"Comp 101_13"},{"name":"Comp 101_14"},{"name":"Comp 101_15"},{"name":"Comp 101_16"},{"name":"Comp 101_17"},{"name":"Comp 101_18"},{"name":"Comp 101_19"},{"name":"Comp 101_20"},{"name":"Comp 101_21"},{"name":"Comp 101_22"},{"name":"Comp 101_23"}]}]}],"animation":[{"duration":72,"playTimes":0,"name":"sdmn_megawin_ani","bone":[{"name":"Comp 101_00","scaleFrame":[{"duration":72,"x":4,"y":4}]}],"slot":[{"name":"Comp 101_00","displayFrame":[{"duration":2},{"duration":2,"value":1},{"duration":2,"value":2},{"duration":2,"value":3},{"duration":2,"value":4},{"duration":2,"value":5},{"duration":2,"value":6},{"duration":2,"value":7},{"duration":2,"value":8},{"duration":2,"value":9},{"duration":2,"value":10},{"duration":2,"value":11},{"duration":2,"value":12},{"duration":2,"value":13},{"duration":2,"value":14},{"duration":2,"value":15},{"duration":2,"value":16},{"duration":2,"value":17},{"duration":2,"value":18},{"duration":2,"value":19},{"duration":2,"value":20},{"duration":2,"value":21},{"duration":2,"value":22},{"duration":26,"value":23}],"colorFrame":[{"duration":46},{"duration":2},{"duration":24,"value":{"aM":0}}]}]}],"defaultActions":[{"gotoAndPlay":"sdmn_megawin_ani"}]}]}