{"frameRate":24,"name":"bscs_water","version":"5.5","compatibleVersion":"5.5","armature":[{"type":"MovieClip","frameRate":24,"name":"bscs_water","bone":[{"name":"root"},{"name":"Comp 4_00","parent":"root"},{"name":"水","parent":"root"}],"slot":[{"displayIndex":-1,"name":"水","parent":"水"},{"displayIndex":-1,"name":"Comp 4_00","parent":"Comp 4_00"}],"skin":[{"slot":[{"name":"Comp 4_00","display":[{"name":"Comp 4_00"},{"name":"Comp 4_01"},{"name":"Comp 4_02"},{"name":"Comp 4_03"},{"name":"Comp 4_04"},{"name":"Comp 4_05"},{"name":"Comp 4_06"},{"name":"Comp 4_07"},{"name":"Comp 4_08"},{"name":"Comp 4_09"},{"name":"Comp 4_10"},{"name":"Comp 4_11"}]},{"name":"水","display":[{"name":"水"}]}]}],"animation":[{"duration":24,"playTimes":0,"name":"bscs_water","bone":[{"name":"Comp 4_00","scaleFrame":[{"duration":24,"x":2.01,"y":2}]},{"name":"水","translateFrame":[{"duration":24,"y":302}]}],"slot":[{"name":"Comp 4_00","displayFrame":[{"duration":2},{"duration":2,"value":1},{"duration":2,"value":2},{"duration":2,"value":3},{"duration":2,"value":4},{"duration":2,"value":5},{"duration":2,"value":6},{"duration":2,"value":7},{"duration":2,"value":8},{"duration":2,"value":9},{"duration":2,"value":10},{"duration":2,"value":11}]},{"name":"水","displayFrame":[{"duration":24}]}]}],"defaultActions":[{"gotoAndPlay":"bscs_water"}]}]}