{"frameRate":24,"isGlobal":0,"name":"snyx_winshine","version":"5.5","armature":[{"defaultActions":[{"gotoAndPlay":"snyx_winshine"}],"skin":[{"name":"","slot":[{"display":[{"path":"fff561","type":"image","name":"fff561","transform":{}}],"blendMode":"add","name":"fff561"},{"display":[{"path":"fff561","type":"image","name":"fff561","transform":{}}],"blendMode":"add","name":"fff5611"}]}],"animation":[{"frame":[],"duration":120,"ik":[],"bone":[{"translateFrame":[],"scaleFrame":[],"name":"root","rotateFrame":[]},{"translateFrame":[],"scaleFrame":[],"name":"fff561","rotateFrame":[]},{"translateFrame":[],"scaleFrame":[],"name":"fff5611","rotateFrame":[{"tweenEasing":0,"duration":60},{"tweenEasing":0,"duration":60,"rotate":180},{"duration":0}]},{"translateFrame":[],"scaleFrame":[],"name":"fff5612","rotateFrame":[]},{"translateFrame":[],"scaleFrame":[],"name":"fff56111","rotateFrame":[{"tweenEasing":0,"duration":59},{"tweenEasing":0,"duration":2,"rotate":183},{"tweenEasing":0,"duration":59,"rotate":177},{"duration":0}]}],"slot":[{"colorFrame":[{"duration":120,"color":{"gM":90,"bM":54}}],"displayFrame":[],"name":"fff561"},{"colorFrame":[{"duration":120,"color":{"rM":35,"gM":35,"bM":35}}],"displayFrame":[],"name":"fff5611"}],"ffd":[],"name":"snyx_winshine","playTimes":0}],"ik":[],"frameRate":24,"bone":[{"name":"root","transform":{}},{"length":59,"transform":{"scX":6,"scY":3.5},"parent":"root","name":"fff5612"},{"length":59,"transform":{"scX":7,"scY":4},"parent":"root","name":"fff561"},{"length":46,"transform":{},"parent":"fff561","name":"fff5611"},{"length":46,"transform":{},"parent":"fff5612","name":"fff56111"}],"aabb":{"width":256,"y":-128,"height":256,"x":-128},"slot":[{"blendMode":"add","parent":"fff5611","name":"fff561","color":{"gM":56,"bM":0}},{"blendMode":"add","z":1,"parent":"fff56111","name":"fff5611","color":{}}],"type":"Armature","name":"snyx_winshine"}]}